{
  "generated_at": "2026-07-07T15:40:05Z",
  "exchange": "kraken",
  "cache_hit": false,
  "portfolio": {
    "total_usd": 7.01,
    "stablecoins_usd": 0.25,
    "balances": [
      {
        "asset": "PENGU",
        "symbol": "PENGU",
        "coingecko_id": "pudgy-penguins",
        "qty": 360.28,
        "price_usd": 0.00662975,
        "usd_value": 2.39,
        "change_24h_pct": -0.59,
        "avg_buy": null,
        "pnl_pct": null,
        "is_stablecoin": false
      },
      {
        "asset": "SOL",
        "symbol": "SOL",
        "coingecko_id": "solana",
        "qty": 0.029179903,
        "price_usd": 82.03,
        "usd_value": 2.39,
        "change_24h_pct": 1.66,
        "avg_buy": 151.0,
        "pnl_pct": -45.7,
        "is_stablecoin": false
      },
      {
        "asset": "XETH",
        "symbol": "ETH",
        "coingecko_id": "ethereum",
        "qty": 0.0004245732,
        "price_usd": 1793.29,
        "usd_value": 0.76,
        "change_24h_pct": 1.13,
        "avg_buy": 3151.0,
        "pnl_pct": -43.1,
        "is_stablecoin": false
      },
      {
        "asset": "XXBT",
        "symbol": "BTC",
        "coingecko_id": "bitcoin",
        "qty": 1.073e-05,
        "price_usd": 63818,
        "usd_value": 0.68,
        "change_24h_pct": 1.72,
        "avg_buy": 90111.0,
        "pnl_pct": -29.2,
        "is_stablecoin": false
      },
      {
        "asset": "OPN",
        "symbol": "OPN",
        "coingecko_id": "opinion",
        "qty": 8.428,
        "price_usd": 0.063301,
        "usd_value": 0.53,
        "change_24h_pct": -6.57,
        "avg_buy": 0.3326,
        "pnl_pct": -81.0,
        "is_stablecoin": false
      },
      {
        "asset": "USDT",
        "symbol": "USDT",
        "coingecko_id": "tether",
        "qty": 0.24724672,
        "price_usd": 0.99902,
        "usd_value": 0.25,
        "change_24h_pct": -0.02,
        "avg_buy": null,
        "pnl_pct": null,
        "is_stablecoin": true
      },
      {
        "asset": "BABY",
        "symbol": "BABY",
        "coingecko_id": "babylon",
        "qty": 0.01824,
        "price_usd": 0.01396328,
        "usd_value": 0.0,
        "change_24h_pct": 3.85,
        "avg_buy": 0.028,
        "pnl_pct": -50.1,
        "is_stablecoin": false
      },
      {
        "asset": "BONK",
        "symbol": "BONK",
        "coingecko_id": null,
        "qty": 11.09,
        "price_usd": null,
        "usd_value": 0.0,
        "change_24h_pct": null,
        "avg_buy": null,
        "pnl_pct": null,
        "is_stablecoin": false
      },
      {
        "asset": "EIGEN",
        "symbol": "EIGEN",
        "coingecko_id": "eigenlayer",
        "qty": 0.006657,
        "price_usd": 0.229507,
        "usd_value": 0.0,
        "change_24h_pct": 2.34,
        "avg_buy": 0.3,
        "pnl_pct": -23.5,
        "is_stablecoin": false
      },
      {
        "asset": "ETH.B",
        "symbol": "ETH.B",
        "coingecko_id": null,
        "qty": 0.0018778163,
        "price_usd": null,
        "usd_value": 0.0,
        "change_24h_pct": null,
        "avg_buy": null,
        "pnl_pct": null,
        "is_stablecoin": false
      },
      {
        "asset": "FARTCOIN",
        "symbol": "FARTCOIN",
        "coingecko_id": null,
        "qty": 0.00031,
        "price_usd": null,
        "usd_value": 0.0,
        "change_24h_pct": null,
        "avg_buy": null,
        "pnl_pct": null,
        "is_stablecoin": false
      },
      {
        "asset": "PEPE",
        "symbol": "PEPE",
        "coingecko_id": null,
        "qty": 18.39,
        "price_usd": null,
        "usd_value": 0.0,
        "change_24h_pct": null,
        "avg_buy": null,
        "pnl_pct": null,
        "is_stablecoin": false
      },
      {
        "asset": "SHIB",
        "symbol": "SHIB",
        "coingecko_id": null,
        "qty": 12.3695,
        "price_usd": null,
        "usd_value": 0.0,
        "change_24h_pct": null,
        "avg_buy": null,
        "pnl_pct": null,
        "is_stablecoin": false
      },
      {
        "asset": "USDG",
        "symbol": "USDG",
        "coingecko_id": null,
        "qty": 0.23155506,
        "price_usd": null,
        "usd_value": 0.0,
        "change_24h_pct": null,
        "avg_buy": null,
        "pnl_pct": null,
        "is_stablecoin": false
      },
      {
        "asset": "USDG.B",
        "symbol": "USDG.B",
        "coingecko_id": null,
        "qty": 1.09837168,
        "price_usd": null,
        "usd_value": 0.0,
        "change_24h_pct": null,
        "avg_buy": null,
        "pnl_pct": null,
        "is_stablecoin": false
      },
      {
        "asset": "XBT.B",
        "symbol": "XBT.B",
        "coingecko_id": null,
        "qty": 6.38841e-05,
        "price_usd": null,
        "usd_value": 0.0,
        "change_24h_pct": null,
        "avg_buy": null,
        "pnl_pct": null,
        "is_stablecoin": false
      },
      {
        "asset": "XBT.M",
        "symbol": "XBT.M",
        "coingecko_id": null,
        "qty": 1.04659e-05,
        "price_usd": null,
        "usd_value": 0.0,
        "change_24h_pct": null,
        "avg_buy": null,
        "pnl_pct": null,
        "is_stablecoin": false
      },
      {
        "asset": "XXDG",
        "symbol": "XXDG",
        "coingecko_id": null,
        "qty": 0.00073306,
        "price_usd": null,
        "usd_value": 0.0,
        "change_24h_pct": null,
        "avg_buy": null,
        "pnl_pct": null,
        "is_stablecoin": false
      },
      {
        "asset": "XXRP",
        "symbol": "XXRP",
        "coingecko_id": null,
        "qty": 2.5177864,
        "price_usd": null,
        "usd_value": 0.0,
        "change_24h_pct": null,
        "avg_buy": null,
        "pnl_pct": null,
        "is_stablecoin": false
      },
      {
        "asset": "ZEUR",
        "symbol": "ZEUR",
        "coingecko_id": null,
        "qty": 0.0062,
        "price_usd": null,
        "usd_value": 0.0,
        "change_24h_pct": null,
        "avg_buy": null,
        "pnl_pct": null,
        "is_stablecoin": false
      },
      {
        "asset": "ZUSD",
        "symbol": "ZUSD",
        "coingecko_id": "usd-coin",
        "qty": 0.0014,
        "price_usd": 0.999889,
        "usd_value": 0.0,
        "change_24h_pct": 0.0,
        "avg_buy": null,
        "pnl_pct": null,
        "is_stablecoin": true
      },
      {
        "asset": "TSMx.T",
        "symbol": "TSMx.T",
        "coingecko_id": null,
        "qty": 0.002864,
        "price_usd": null,
        "usd_value": 0.0,
        "change_24h_pct": null,
        "avg_buy": null,
        "pnl_pct": null,
        "is_stablecoin": false
      }
    ],
    "open_orders": [],
    "recent_trades": [
      {
        "order_id": "OV4QV3-FH7BV-XNHHYD",
        "pair": "PENGUUSD",
        "type": "sell",
        "order_type": "limit",
        "price_executed": 0.00704,
        "volume": 710.32817,
        "volume_filled": 710.32817,
        "cost_usd": 5.00142,
        "fee_usd": 0.02001,
        "status": "closed",
        "closed_at": "2026-04-15T14:00:44Z"
      }
    ],
    "prices": {
      "BABYUSD": {
        "bid": 0.01394,
        "ask": 0.01396,
        "last": 0.01396,
        "high_24h": 0.0141,
        "low_24h": 0.01335,
        "volume_24h": 6367681.1393,
        "vwap_24h": 0.013778504,
        "trades_24h": 1690
      },
      "EIGENUSD": {
        "bid": 0.2298,
        "ask": 0.23,
        "last": 0.2305,
        "high_24h": 0.2365,
        "low_24h": 0.2209,
        "volume_24h": 431427.13977,
        "vwap_24h": 0.2284739,
        "trades_24h": 943
      },
      "XETHZUSD": {
        "bid": 1790.9,
        "ask": 1790.91,
        "last": 1792.13,
        "high_24h": 1834.73,
        "low_24h": 1756.4,
        "volume_24h": 26410.37959282,
        "vwap_24h": 1791.12349,
        "trades_24h": 24876
      },
      "OPNUSD": {
        "bid": 0.0633,
        "ask": 0.0635,
        "last": 0.0633,
        "high_24h": 0.0687,
        "low_24h": 0.063,
        "volume_24h": 173232.54596,
        "vwap_24h": 0.06677539,
        "trades_24h": 104
      },
      "PENGUUSD": {
        "bid": 0.006628,
        "ask": 0.006629,
        "last": 0.006635,
        "high_24h": 0.006894,
        "low_24h": 0.006488,
        "volume_24h": 32544550.52835,
        "vwap_24h": 0.006688179,
        "trades_24h": 1619
      },
      "SOLUSD": {
        "bid": 81.97,
        "ask": 82.0,
        "last": 82.0,
        "high_24h": 83.65,
        "low_24h": 80.44,
        "volume_24h": 309935.4017362,
        "vwap_24h": 81.62673,
        "trades_24h": 18942
      },
      "XXBTZUSD": {
        "bid": 63740.9,
        "ask": 63741.0,
        "last": 63745.2,
        "high_24h": 64675.0,
        "low_24h": 62318.6,
        "volume_24h": 2771.87123843,
        "vwap_24h": 63496.04706,
        "trades_24h": 50359
      }
    }
  }
}