{
  "generated_at": "2026-03-27T15:13:39Z",
  "exchange": "kraken",
  "cache_hit": false,
  "portfolio": {
    "total_usd": 14.48,
    "stablecoins_usd": 0.01,
    "balances": [
      {
        "asset": "PENGU",
        "symbol": "PENGU",
        "coingecko_id": "pudgy-penguins",
        "qty": 1873.2359,
        "price_usd": 0.00653225,
        "usd_value": 12.24,
        "change_24h_pct": -5.68,
        "avg_buy": null,
        "pnl_pct": null,
        "is_stablecoin": false
      },
      {
        "asset": "XXBT",
        "symbol": "BTC",
        "coingecko_id": "bitcoin",
        "qty": 2.364e-05,
        "price_usd": 66183,
        "usd_value": 1.56,
        "change_24h_pct": -4.21,
        "avg_buy": 90111.0,
        "pnl_pct": -26.6,
        "is_stablecoin": false
      },
      {
        "asset": "OPN",
        "symbol": "OPN",
        "coingecko_id": "opinion",
        "qty": 3.498,
        "price_usd": 0.189345,
        "usd_value": 0.66,
        "change_24h_pct": -7.01,
        "avg_buy": 0.3326,
        "pnl_pct": -43.1,
        "is_stablecoin": false
      },
      {
        "asset": "USDT",
        "symbol": "USDT",
        "coingecko_id": "tether",
        "qty": 0.01002492,
        "price_usd": 0.999447,
        "usd_value": 0.01,
        "change_24h_pct": 0.0,
        "avg_buy": null,
        "pnl_pct": null,
        "is_stablecoin": true
      },
      {
        "asset": "XETH",
        "symbol": "ETH",
        "coingecko_id": "ethereum",
        "qty": 4.0023e-06,
        "price_usd": 1990.18,
        "usd_value": 0.01,
        "change_24h_pct": -3.61,
        "avg_buy": 3151.0,
        "pnl_pct": -36.8,
        "is_stablecoin": false
      },
      {
        "asset": "BABY",
        "symbol": "BABY",
        "coingecko_id": "babylon",
        "qty": 0.0038,
        "price_usd": 0.01275972,
        "usd_value": 0.0,
        "change_24h_pct": -2.96,
        "avg_buy": 0.028,
        "pnl_pct": -54.4,
        "is_stablecoin": false
      },
      {
        "asset": "EIGEN",
        "symbol": "EIGEN",
        "coingecko_id": "eigenlayer",
        "qty": 0.003627,
        "price_usd": 0.17931,
        "usd_value": 0.0,
        "change_24h_pct": -4.67,
        "avg_buy": 0.3,
        "pnl_pct": -40.2,
        "is_stablecoin": false
      },
      {
        "asset": "ETH.B",
        "symbol": "ETH.B",
        "coingecko_id": null,
        "qty": 0.0018678791,
        "price_usd": null,
        "usd_value": 0.0,
        "change_24h_pct": null,
        "avg_buy": null,
        "pnl_pct": null,
        "is_stablecoin": false
      },
      {
        "asset": "SOL",
        "symbol": "SOL",
        "coingecko_id": "solana",
        "qty": 6.265e-06,
        "price_usd": 83.23,
        "usd_value": 0.0,
        "change_24h_pct": -4.72,
        "avg_buy": 151.0,
        "pnl_pct": -44.9,
        "is_stablecoin": false
      },
      {
        "asset": "USDG",
        "symbol": "USDG",
        "coingecko_id": null,
        "qty": 1.08398253,
        "price_usd": null,
        "usd_value": 0.0,
        "change_24h_pct": null,
        "avg_buy": null,
        "pnl_pct": null,
        "is_stablecoin": false
      },
      {
        "asset": "XBT.B",
        "symbol": "XBT.B",
        "coingecko_id": null,
        "qty": 6.38565e-05,
        "price_usd": null,
        "usd_value": 0.0,
        "change_24h_pct": null,
        "avg_buy": null,
        "pnl_pct": null,
        "is_stablecoin": false
      },
      {
        "asset": "XBT.M",
        "symbol": "XBT.M",
        "coingecko_id": null,
        "qty": 1.04629e-05,
        "price_usd": null,
        "usd_value": 0.0,
        "change_24h_pct": null,
        "avg_buy": null,
        "pnl_pct": null,
        "is_stablecoin": false
      },
      {
        "asset": "ZEUR",
        "symbol": "ZEUR",
        "coingecko_id": null,
        "qty": 0.0092,
        "price_usd": null,
        "usd_value": 0.0,
        "change_24h_pct": null,
        "avg_buy": null,
        "pnl_pct": null,
        "is_stablecoin": false
      }
    ],
    "open_orders": [],
    "recent_trades": [],
    "prices": {
      "BABYUSD": {
        "bid": 0.01273,
        "ask": 0.01276,
        "last": 0.01275,
        "high_24h": 0.01328,
        "low_24h": 0.01252,
        "volume_24h": 1185431.13146,
        "vwap_24h": 0.012966972,
        "trades_24h": 310
      },
      "EIGENUSD": {
        "bid": 0.1793,
        "ask": 0.18,
        "last": 0.1793,
        "high_24h": 0.1879,
        "low_24h": 0.1773,
        "volume_24h": 873469.18671,
        "vwap_24h": 0.1824687,
        "trades_24h": 407
      },
      "XETHZUSD": {
        "bid": 1989.38,
        "ask": 1989.39,
        "last": 1989.39,
        "high_24h": 2078.93,
        "low_24h": 1969.4,
        "volume_24h": 39990.82886662,
        "vwap_24h": 2033.20363,
        "trades_24h": 27042
      },
      "OPNUSD": {
        "bid": 0.1886,
        "ask": 0.19,
        "last": 0.1896,
        "high_24h": 0.2187,
        "low_24h": 0.1854,
        "volume_24h": 482036.27616,
        "vwap_24h": 0.19756384,
        "trades_24h": 906
      },
      "PENGUUSD": {
        "bid": 0.006526,
        "ask": 0.006527,
        "last": 0.00653,
        "high_24h": 0.006922,
        "low_24h": 0.006491,
        "volume_24h": 106754460.57521,
        "vwap_24h": 0.006735197,
        "trades_24h": 3054
      },
      "SOLUSD": {
        "bid": 83.15,
        "ask": 83.16,
        "last": 83.17,
        "high_24h": 87.73,
        "low_24h": 82.47,
        "volume_24h": 387603.19524794,
        "vwap_24h": 85.32121,
        "trades_24h": 21179
      },
      "XXBTZUSD": {
        "bid": 66197.6,
        "ask": 66197.7,
        "last": 66197.7,
        "high_24h": 69402.8,
        "low_24h": 65680.3,
        "volume_24h": 3361.77844227,
        "vwap_24h": 67676.66266,
        "trades_24h": 68216
      }
    }
  }
}