{
  "generated_at": "2026-06-19T15:57:43Z",
  "exchange": "kraken",
  "cache_hit": false,
  "portfolio": {
    "total_usd": 6.69,
    "stablecoins_usd": 0.25,
    "balances": [
      {
        "asset": "PENGU",
        "symbol": "PENGU",
        "coingecko_id": "pudgy-penguins",
        "qty": 360.2592,
        "price_usd": 0.00658809,
        "usd_value": 2.37,
        "change_24h_pct": 1.39,
        "avg_buy": null,
        "pnl_pct": null,
        "is_stablecoin": false
      },
      {
        "asset": "SOL",
        "symbol": "SOL",
        "coingecko_id": "solana",
        "qty": 0.0291470057,
        "price_usd": 69.27,
        "usd_value": 2.02,
        "change_24h_pct": 1.29,
        "avg_buy": 151.0,
        "pnl_pct": -54.1,
        "is_stablecoin": false
      },
      {
        "asset": "XETH",
        "symbol": "ETH",
        "coingecko_id": "ethereum",
        "qty": 0.0004243841,
        "price_usd": 1707.2,
        "usd_value": 0.72,
        "change_24h_pct": 1.56,
        "avg_buy": 3151.0,
        "pnl_pct": -45.8,
        "is_stablecoin": false
      },
      {
        "asset": "XXBT",
        "symbol": "BTC",
        "coingecko_id": "bitcoin",
        "qty": 1.073e-05,
        "price_usd": 63196,
        "usd_value": 0.68,
        "change_24h_pct": 1.43,
        "avg_buy": 90111.0,
        "pnl_pct": -29.9,
        "is_stablecoin": false
      },
      {
        "asset": "OPN",
        "symbol": "OPN",
        "coingecko_id": "opinion",
        "qty": 8.428,
        "price_usd": 0.076745,
        "usd_value": 0.65,
        "change_24h_pct": 9.44,
        "avg_buy": 0.3326,
        "pnl_pct": -76.9,
        "is_stablecoin": false
      },
      {
        "asset": "USDT",
        "symbol": "USDT",
        "coingecko_id": "tether",
        "qty": 0.24671441,
        "price_usd": 0.999089,
        "usd_value": 0.25,
        "change_24h_pct": 0.12,
        "avg_buy": null,
        "pnl_pct": null,
        "is_stablecoin": true
      },
      {
        "asset": "BABY",
        "symbol": "BABY",
        "coingecko_id": "babylon",
        "qty": 0.01783,
        "price_usd": 0.01403386,
        "usd_value": 0.0,
        "change_24h_pct": -3.82,
        "avg_buy": 0.028,
        "pnl_pct": -49.9,
        "is_stablecoin": false
      },
      {
        "asset": "BONK",
        "symbol": "BONK",
        "coingecko_id": null,
        "qty": 7.18,
        "price_usd": null,
        "usd_value": 0.0,
        "change_24h_pct": null,
        "avg_buy": null,
        "pnl_pct": null,
        "is_stablecoin": false
      },
      {
        "asset": "EIGEN",
        "symbol": "EIGEN",
        "coingecko_id": "eigenlayer",
        "qty": 0.005941,
        "price_usd": 0.228762,
        "usd_value": 0.0,
        "change_24h_pct": 13.47,
        "avg_buy": 0.3,
        "pnl_pct": -23.7,
        "is_stablecoin": false
      },
      {
        "asset": "ETH.B",
        "symbol": "ETH.B",
        "coingecko_id": null,
        "qty": 0.0018760235,
        "price_usd": null,
        "usd_value": 0.0,
        "change_24h_pct": null,
        "avg_buy": null,
        "pnl_pct": null,
        "is_stablecoin": false
      },
      {
        "asset": "FARTCOIN",
        "symbol": "FARTCOIN",
        "coingecko_id": null,
        "qty": 0.0002,
        "price_usd": null,
        "usd_value": 0.0,
        "change_24h_pct": null,
        "avg_buy": null,
        "pnl_pct": null,
        "is_stablecoin": false
      },
      {
        "asset": "PEPE",
        "symbol": "PEPE",
        "coingecko_id": null,
        "qty": 11.91,
        "price_usd": null,
        "usd_value": 0.0,
        "change_24h_pct": null,
        "avg_buy": null,
        "pnl_pct": null,
        "is_stablecoin": false
      },
      {
        "asset": "SHIB",
        "symbol": "SHIB",
        "coingecko_id": null,
        "qty": 8.0131,
        "price_usd": null,
        "usd_value": 0.0,
        "change_24h_pct": null,
        "avg_buy": null,
        "pnl_pct": null,
        "is_stablecoin": false
      },
      {
        "asset": "USDG",
        "symbol": "USDG",
        "coingecko_id": null,
        "qty": 0.23105653,
        "price_usd": null,
        "usd_value": 0.0,
        "change_24h_pct": null,
        "avg_buy": null,
        "pnl_pct": null,
        "is_stablecoin": false
      },
      {
        "asset": "USDG.B",
        "symbol": "USDG.B",
        "coingecko_id": null,
        "qty": 1.09553479,
        "price_usd": null,
        "usd_value": 0.0,
        "change_24h_pct": null,
        "avg_buy": null,
        "pnl_pct": null,
        "is_stablecoin": false
      },
      {
        "asset": "XBT.B",
        "symbol": "XBT.B",
        "coingecko_id": null,
        "qty": 6.38786e-05,
        "price_usd": null,
        "usd_value": 0.0,
        "change_24h_pct": null,
        "avg_buy": null,
        "pnl_pct": null,
        "is_stablecoin": false
      },
      {
        "asset": "XBT.M",
        "symbol": "XBT.M",
        "coingecko_id": null,
        "qty": 1.04653e-05,
        "price_usd": null,
        "usd_value": 0.0,
        "change_24h_pct": null,
        "avg_buy": null,
        "pnl_pct": null,
        "is_stablecoin": false
      },
      {
        "asset": "XXDG",
        "symbol": "XXDG",
        "coingecko_id": null,
        "qty": 0.00047488,
        "price_usd": null,
        "usd_value": 0.0,
        "change_24h_pct": null,
        "avg_buy": null,
        "pnl_pct": null,
        "is_stablecoin": false
      },
      {
        "asset": "XXRP",
        "symbol": "XXRP",
        "coingecko_id": null,
        "qty": 3.51760846,
        "price_usd": null,
        "usd_value": 0.0,
        "change_24h_pct": null,
        "avg_buy": null,
        "pnl_pct": null,
        "is_stablecoin": false
      },
      {
        "asset": "ZEUR",
        "symbol": "ZEUR",
        "coingecko_id": null,
        "qty": 4.2049,
        "price_usd": null,
        "usd_value": 0.0,
        "change_24h_pct": null,
        "avg_buy": null,
        "pnl_pct": null,
        "is_stablecoin": false
      },
      {
        "asset": "ZUSD",
        "symbol": "ZUSD",
        "coingecko_id": "usd-coin",
        "qty": 0.0014,
        "price_usd": 0.999876,
        "usd_value": 0.0,
        "change_24h_pct": 0.01,
        "avg_buy": null,
        "pnl_pct": null,
        "is_stablecoin": true
      },
      {
        "asset": "TSMx.T",
        "symbol": "TSMx.T",
        "coingecko_id": null,
        "qty": 0.002864,
        "price_usd": null,
        "usd_value": 0.0,
        "change_24h_pct": null,
        "avg_buy": null,
        "pnl_pct": null,
        "is_stablecoin": false
      }
    ],
    "open_orders": [],
    "recent_trades": [
      {
        "order_id": "OV4QV3-FH7BV-XNHHYD",
        "pair": "PENGUUSD",
        "type": "sell",
        "order_type": "limit",
        "price_executed": 0.00704,
        "volume": 710.32817,
        "volume_filled": 710.32817,
        "cost_usd": 5.00142,
        "fee_usd": 0.02001,
        "status": "closed",
        "closed_at": "2026-04-15T14:00:44Z"
      }
    ],
    "prices": {
      "BABYUSD": {
        "bid": 0.01407,
        "ask": 0.01408,
        "last": 0.01409,
        "high_24h": 0.01498,
        "low_24h": 0.01389,
        "volume_24h": 9124221.52329,
        "vwap_24h": 0.014365636,
        "trades_24h": 1956
      },
      "EIGENUSD": {
        "bid": 0.2286,
        "ask": 0.2289,
        "last": 0.2284,
        "high_24h": 0.2328,
        "low_24h": 0.2011,
        "volume_24h": 1106302.5749,
        "vwap_24h": 0.2212735,
        "trades_24h": 1058
      },
      "XETHZUSD": {
        "bid": 1705.83,
        "ask": 1706.13,
        "last": 1706.09,
        "high_24h": 1717.71,
        "low_24h": 1669.56,
        "volume_24h": 13357.02379388,
        "vwap_24h": 1692.23202,
        "trades_24h": 16378
      },
      "OPNUSD": {
        "bid": 0.0767,
        "ask": 0.077,
        "last": 0.0775,
        "high_24h": 0.0787,
        "low_24h": 0.0699,
        "volume_24h": 366846.29712,
        "vwap_24h": 0.07492079,
        "trades_24h": 264
      },
      "PENGUUSD": {
        "bid": 0.006573,
        "ask": 0.006577,
        "last": 0.006579,
        "high_24h": 0.006786,
        "low_24h": 0.006337,
        "volume_24h": 66740827.22601,
        "vwap_24h": 0.006544225,
        "trades_24h": 2409
      },
      "SOLUSD": {
        "bid": 69.25,
        "ask": 69.27,
        "last": 69.27,
        "high_24h": 69.99,
        "low_24h": 67.85,
        "volume_24h": 431059.76167994,
        "vwap_24h": 68.76958,
        "trades_24h": 18710
      },
      "XXBTZUSD": {
        "bid": 63157.1,
        "ask": 63158.5,
        "last": 63156.7,
        "high_24h": 63345.6,
        "low_24h": 62187.0,
        "volume_24h": 2163.30053147,
        "vwap_24h": 62698.78799,
        "trades_24h": 47953
      }
    }
  }
}